{
  "type": "Program",
  "start": 0,
  "end": 863,
  "loc": {
    "start": {
      "line": 1,
      "column": 0
    },
    "end": {
      "line": 23,
      "column": 0
    }
  },
  "sourceType": "module",
  "body": [
    {
      "type": "ImportDeclaration",
      "start": 622,
      "end": 668,
      "loc": {
        "start": {
          "line": 15,
          "column": 0
        },
        "end": {
          "line": 15,
          "column": 46
        }
      },
      "specifiers": [
        {
          "type": "ImportDefaultSpecifier",
          "start": 629,
          "end": 639,
          "loc": {
            "start": {
              "line": 15,
              "column": 7
            },
            "end": {
              "line": 15,
              "column": 17
            }
          },
          "local": {
            "type": "Identifier",
            "start": 629,
            "end": 639,
            "loc": {
              "start": {
                "line": 15,
                "column": 7
              },
              "end": {
                "line": 15,
                "column": 17
              }
            },
            "name": "PushClient",
            "leadingComments": null
          },
          "leadingComments": null
        }
      ],
      "importKind": "value",
      "source": {
        "type": "Literal",
        "start": 645,
        "end": 667,
        "loc": {
          "start": {
            "line": 15,
            "column": 23
          },
          "end": {
            "line": 15,
            "column": 45
          }
        },
        "value": "./client/push-client",
        "rawValue": "./client/push-client",
        "raw": "'./client/push-client'"
      },
      "leadingComments": [
        {
          "type": "Block",
          "value": "\n  Copyright 2015 Google Inc. All Rights Reserved.\n  Licensed under the Apache License, Version 2.0 (the \"License\");\n  you may not use this file except in compliance with the License.\n  You may obtain a copy of the License at\n      http://www.apache.org/licenses/LICENSE-2.0\n  Unless required by applicable law or agreed to in writing, software\n  distributed under the License is distributed on an \"AS IS\" BASIS,\n  WITHOUT WARRANTIES OR CONDITIONS OF ANY KIND, either express or implied.\n  See the License for the specific language governing permissions and\n  limitations under the License.\n",
          "start": 0,
          "end": 595,
          "loc": {
            "start": {
              "line": 1,
              "column": 0
            },
            "end": {
              "line": 12,
              "column": 2
            }
          },
          "range": [
            0,
            595
          ]
        },
        {
          "type": "Block",
          "value": " eslint-env browser ",
          "start": 596,
          "end": 620,
          "loc": {
            "start": {
              "line": 13,
              "column": 0
            },
            "end": {
              "line": 13,
              "column": 24
            }
          },
          "range": [
            596,
            620
          ]
        }
      ]
    },
    {
      "type": "ImportDeclaration",
      "start": 669,
      "end": 721,
      "loc": {
        "start": {
          "line": 16,
          "column": 0
        },
        "end": {
          "line": 16,
          "column": 52
        }
      },
      "specifiers": [
        {
          "type": "ImportDefaultSpecifier",
          "start": 676,
          "end": 689,
          "loc": {
            "start": {
              "line": 16,
              "column": 7
            },
            "end": {
              "line": 16,
              "column": 20
            }
          },
          "local": {
            "type": "Identifier",
            "start": 676,
            "end": 689,
            "loc": {
              "start": {
                "line": 16,
                "column": 7
              },
              "end": {
                "line": 16,
                "column": 20
              }
            },
            "name": "serverUpdater"
          }
        }
      ],
      "importKind": "value",
      "source": {
        "type": "Literal",
        "start": 695,
        "end": 720,
        "loc": {
          "start": {
            "line": 16,
            "column": 26
          },
          "end": {
            "line": 16,
            "column": 51
          }
        },
        "value": "./client/server-updater",
        "rawValue": "./client/server-updater",
        "raw": "'./client/server-updater'"
      }
    },
    {
      "type": "ExpressionStatement",
      "start": 723,
      "end": 755,
      "loc": {
        "start": {
          "line": 18,
          "column": 0
        },
        "end": {
          "line": 18,
          "column": 32
        }
      },
      "expression": {
        "type": "AssignmentExpression",
        "start": 723,
        "end": 754,
        "loc": {
          "start": {
            "line": 18,
            "column": 0
          },
          "end": {
            "line": 18,
            "column": 31
          }
        },
        "operator": "=",
        "left": {
          "type": "MemberExpression",
          "start": 723,
          "end": 734,
          "loc": {
            "start": {
              "line": 18,
              "column": 0
            },
            "end": {
              "line": 18,
              "column": 11
            }
          },
          "object": {
            "type": "Identifier",
            "start": 723,
            "end": 729,
            "loc": {
              "start": {
                "line": 18,
                "column": 0
              },
              "end": {
                "line": 18,
                "column": 6
              }
            },
            "name": "window"
          },
          "property": {
            "type": "Identifier",
            "start": 730,
            "end": 734,
            "loc": {
              "start": {
                "line": 18,
                "column": 7
              },
              "end": {
                "line": 18,
                "column": 11
              }
            },
            "name": "goog"
          },
          "computed": false
        },
        "right": {
          "type": "LogicalExpression",
          "start": 737,
          "end": 754,
          "loc": {
            "start": {
              "line": 18,
              "column": 14
            },
            "end": {
              "line": 18,
              "column": 31
            }
          },
          "left": {
            "type": "MemberExpression",
            "start": 737,
            "end": 748,
            "loc": {
              "start": {
                "line": 18,
                "column": 14
              },
              "end": {
                "line": 18,
                "column": 25
              }
            },
            "object": {
              "type": "Identifier",
              "start": 737,
              "end": 743,
              "loc": {
                "start": {
                  "line": 18,
                  "column": 14
                },
                "end": {
                  "line": 18,
                  "column": 20
                }
              },
              "name": "window"
            },
            "property": {
              "type": "Identifier",
              "start": 744,
              "end": 748,
              "loc": {
                "start": {
                  "line": 18,
                  "column": 21
                },
                "end": {
                  "line": 18,
                  "column": 25
                }
              },
              "name": "goog"
            },
            "computed": false
          },
          "operator": "||",
          "right": {
            "type": "ObjectExpression",
            "start": 752,
            "end": 754,
            "loc": {
              "start": {
                "line": 18,
                "column": 29
              },
              "end": {
                "line": 18,
                "column": 31
              }
            },
            "properties": []
          }
        }
      }
    },
    {
      "type": "ExpressionStatement",
      "start": 756,
      "end": 862,
      "loc": {
        "start": {
          "line": 19,
          "column": 0
        },
        "end": {
          "line": 22,
          "column": 2
        }
      },
      "expression": {
        "type": "AssignmentExpression",
        "start": 756,
        "end": 861,
        "loc": {
          "start": {
            "line": 19,
            "column": 0
          },
          "end": {
            "line": 22,
            "column": 1
          }
        },
        "operator": "=",
        "left": {
          "type": "MemberExpression",
          "start": 756,
          "end": 774,
          "loc": {
            "start": {
              "line": 19,
              "column": 0
            },
            "end": {
              "line": 19,
              "column": 18
            }
          },
          "object": {
            "type": "MemberExpression",
            "start": 756,
            "end": 767,
            "loc": {
              "start": {
                "line": 19,
                "column": 0
              },
              "end": {
                "line": 19,
                "column": 11
              }
            },
            "object": {
              "type": "Identifier",
              "start": 756,
              "end": 762,
              "loc": {
                "start": {
                  "line": 19,
                  "column": 0
                },
                "end": {
                  "line": 19,
                  "column": 6
                }
              },
              "name": "window"
            },
            "property": {
              "type": "Identifier",
              "start": 763,
              "end": 767,
              "loc": {
                "start": {
                  "line": 19,
                  "column": 7
                },
                "end": {
                  "line": 19,
                  "column": 11
                }
              },
              "name": "goog"
            },
            "computed": false
          },
          "property": {
            "type": "Identifier",
            "start": 768,
            "end": 774,
            "loc": {
              "start": {
                "line": 19,
                "column": 12
              },
              "end": {
                "line": 19,
                "column": 18
              }
            },
            "name": "propel"
          },
          "computed": false
        },
        "right": {
          "type": "LogicalExpression",
          "start": 777,
          "end": 861,
          "loc": {
            "start": {
              "line": 19,
              "column": 21
            },
            "end": {
              "line": 22,
              "column": 1
            }
          },
          "left": {
            "type": "MemberExpression",
            "start": 777,
            "end": 795,
            "loc": {
              "start": {
                "line": 19,
                "column": 21
              },
              "end": {
                "line": 19,
                "column": 39
              }
            },
            "object": {
              "type": "MemberExpression",
              "start": 777,
              "end": 788,
              "loc": {
                "start": {
                  "line": 19,
                  "column": 21
                },
                "end": {
                  "line": 19,
                  "column": 32
                }
              },
              "object": {
                "type": "Identifier",
                "start": 777,
                "end": 783,
                "loc": {
                  "start": {
                    "line": 19,
                    "column": 21
                  },
                  "end": {
                    "line": 19,
                    "column": 27
                  }
                },
                "name": "window"
              },
              "property": {
                "type": "Identifier",
                "start": 784,
                "end": 788,
                "loc": {
                  "start": {
                    "line": 19,
                    "column": 28
                  },
                  "end": {
                    "line": 19,
                    "column": 32
                  }
                },
                "name": "goog"
              },
              "computed": false
            },
            "property": {
              "type": "Identifier",
              "start": 789,
              "end": 795,
              "loc": {
                "start": {
                  "line": 19,
                  "column": 33
                },
                "end": {
                  "line": 19,
                  "column": 39
                }
              },
              "name": "propel"
            },
            "computed": false
          },
          "operator": "||",
          "right": {
            "type": "ObjectExpression",
            "start": 799,
            "end": 861,
            "loc": {
              "start": {
                "line": 19,
                "column": 43
              },
              "end": {
                "line": 22,
                "column": 1
              }
            },
            "properties": [
              {
                "type": "Property",
                "start": 803,
                "end": 827,
                "loc": {
                  "start": {
                    "line": 20,
                    "column": 2
                  },
                  "end": {
                    "line": 20,
                    "column": 26
                  }
                },
                "method": false,
                "shorthand": false,
                "computed": false,
                "key": {
                  "type": "Identifier",
                  "start": 803,
                  "end": 815,
                  "loc": {
                    "start": {
                      "line": 20,
                      "column": 2
                    },
                    "end": {
                      "line": 20,
                      "column": 14
                    }
                  },
                  "name": "PropelClient"
                },
                "value": {
                  "type": "Identifier",
                  "start": 817,
                  "end": 827,
                  "loc": {
                    "start": {
                      "line": 20,
                      "column": 16
                    },
                    "end": {
                      "line": 20,
                      "column": 26
                    }
                  },
                  "name": "PushClient"
                },
                "kind": "init"
              },
              {
                "type": "Property",
                "start": 831,
                "end": 859,
                "loc": {
                  "start": {
                    "line": 21,
                    "column": 2
                  },
                  "end": {
                    "line": 21,
                    "column": 30
                  }
                },
                "method": false,
                "shorthand": false,
                "computed": false,
                "key": {
                  "type": "Identifier",
                  "start": 831,
                  "end": 844,
                  "loc": {
                    "start": {
                      "line": 21,
                      "column": 2
                    },
                    "end": {
                      "line": 21,
                      "column": 15
                    }
                  },
                  "name": "serverUpdater"
                },
                "value": {
                  "type": "Identifier",
                  "start": 846,
                  "end": 859,
                  "loc": {
                    "start": {
                      "line": 21,
                      "column": 17
                    },
                    "end": {
                      "line": 21,
                      "column": 30
                    }
                  },
                  "name": "serverUpdater"
                },
                "kind": "init"
              }
            ]
          }
        }
      }
    }
  ]
}