{
  "type": "Program",
  "start": 0,
  "end": 815,
  "loc": {
    "start": {
      "line": 1,
      "column": 0
    },
    "end": {
      "line": 20,
      "column": 0
    }
  },
  "sourceType": "module",
  "body": [
    {
      "type": "ImportDeclaration",
      "start": 628,
      "end": 692,
      "loc": {
        "start": {
          "line": 15,
          "column": 0
        },
        "end": {
          "line": 15,
          "column": 64
        }
      },
      "specifiers": [
        {
          "type": "ImportDefaultSpecifier",
          "start": 635,
          "end": 654,
          "loc": {
            "start": {
              "line": 15,
              "column": 7
            },
            "end": {
              "line": 15,
              "column": 26
            }
          },
          "local": {
            "type": "Identifier",
            "start": 635,
            "end": 654,
            "loc": {
              "start": {
                "line": 15,
                "column": 7
              },
              "end": {
                "line": 15,
                "column": 26
              }
            },
            "name": "notificationHandler",
            "leadingComments": null
          },
          "leadingComments": null
        }
      ],
      "importKind": "value",
      "source": {
        "type": "Literal",
        "start": 660,
        "end": 691,
        "loc": {
          "start": {
            "line": 15,
            "column": 32
          },
          "end": {
            "line": 15,
            "column": 63
          }
        },
        "value": "./worker/notification-handler",
        "rawValue": "./worker/notification-handler",
        "raw": "'./worker/notification-handler'"
      },
      "leadingComments": [
        {
          "type": "Block",
          "value": "\n  Copyright 2015 Google Inc. All Rights Reserved.\n  Licensed under the Apache License, Version 2.0 (the \"License\");\n  you may not use this file except in compliance with the License.\n  You may obtain a copy of the License at\n      http://www.apache.org/licenses/LICENSE-2.0\n  Unless required by applicable law or agreed to in writing, software\n  distributed under the License is distributed on an \"AS IS\" BASIS,\n  WITHOUT WARRANTIES OR CONDITIONS OF ANY KIND, either express or implied.\n  See the License for the specific language governing permissions and\n  limitations under the License.\n",
          "start": 0,
          "end": 595,
          "loc": {
            "start": {
              "line": 1,
              "column": 0
            },
            "end": {
              "line": 12,
              "column": 2
            }
          },
          "range": [
            0,
            595
          ]
        },
        {
          "type": "Block",
          "value": " eslint-env serviceworker ",
          "start": 596,
          "end": 626,
          "loc": {
            "start": {
              "line": 13,
              "column": 0
            },
            "end": {
              "line": 13,
              "column": 30
            }
          },
          "range": [
            596,
            626
          ]
        }
      ]
    },
    {
      "type": "ExpressionStatement",
      "start": 694,
      "end": 722,
      "loc": {
        "start": {
          "line": 17,
          "column": 0
        },
        "end": {
          "line": 17,
          "column": 28
        }
      },
      "expression": {
        "type": "AssignmentExpression",
        "start": 694,
        "end": 721,
        "loc": {
          "start": {
            "line": 17,
            "column": 0
          },
          "end": {
            "line": 17,
            "column": 27
          }
        },
        "operator": "=",
        "left": {
          "type": "MemberExpression",
          "start": 694,
          "end": 703,
          "loc": {
            "start": {
              "line": 17,
              "column": 0
            },
            "end": {
              "line": 17,
              "column": 9
            }
          },
          "object": {
            "type": "Identifier",
            "start": 694,
            "end": 698,
            "loc": {
              "start": {
                "line": 17,
                "column": 0
              },
              "end": {
                "line": 17,
                "column": 4
              }
            },
            "name": "self"
          },
          "property": {
            "type": "Identifier",
            "start": 699,
            "end": 703,
            "loc": {
              "start": {
                "line": 17,
                "column": 5
              },
              "end": {
                "line": 17,
                "column": 9
              }
            },
            "name": "goog"
          },
          "computed": false
        },
        "right": {
          "type": "LogicalExpression",
          "start": 706,
          "end": 721,
          "loc": {
            "start": {
              "line": 17,
              "column": 12
            },
            "end": {
              "line": 17,
              "column": 27
            }
          },
          "left": {
            "type": "MemberExpression",
            "start": 706,
            "end": 715,
            "loc": {
              "start": {
                "line": 17,
                "column": 12
              },
              "end": {
                "line": 17,
                "column": 21
              }
            },
            "object": {
              "type": "Identifier",
              "start": 706,
              "end": 710,
              "loc": {
                "start": {
                  "line": 17,
                  "column": 12
                },
                "end": {
                  "line": 17,
                  "column": 16
                }
              },
              "name": "self"
            },
            "property": {
              "type": "Identifier",
              "start": 711,
              "end": 715,
              "loc": {
                "start": {
                  "line": 17,
                  "column": 17
                },
                "end": {
                  "line": 17,
                  "column": 21
                }
              },
              "name": "goog"
            },
            "computed": false
          },
          "operator": "||",
          "right": {
            "type": "ObjectExpression",
            "start": 719,
            "end": 721,
            "loc": {
              "start": {
                "line": 17,
                "column": 25
              },
              "end": {
                "line": 17,
                "column": 27
              }
            },
            "properties": []
          }
        }
      }
    },
    {
      "type": "ExpressionStatement",
      "start": 723,
      "end": 765,
      "loc": {
        "start": {
          "line": 18,
          "column": 0
        },
        "end": {
          "line": 18,
          "column": 42
        }
      },
      "expression": {
        "type": "AssignmentExpression",
        "start": 723,
        "end": 764,
        "loc": {
          "start": {
            "line": 18,
            "column": 0
          },
          "end": {
            "line": 18,
            "column": 41
          }
        },
        "operator": "=",
        "left": {
          "type": "MemberExpression",
          "start": 723,
          "end": 739,
          "loc": {
            "start": {
              "line": 18,
              "column": 0
            },
            "end": {
              "line": 18,
              "column": 16
            }
          },
          "object": {
            "type": "MemberExpression",
            "start": 723,
            "end": 732,
            "loc": {
              "start": {
                "line": 18,
                "column": 0
              },
              "end": {
                "line": 18,
                "column": 9
              }
            },
            "object": {
              "type": "Identifier",
              "start": 723,
              "end": 727,
              "loc": {
                "start": {
                  "line": 18,
                  "column": 0
                },
                "end": {
                  "line": 18,
                  "column": 4
                }
              },
              "name": "self"
            },
            "property": {
              "type": "Identifier",
              "start": 728,
              "end": 732,
              "loc": {
                "start": {
                  "line": 18,
                  "column": 5
                },
                "end": {
                  "line": 18,
                  "column": 9
                }
              },
              "name": "goog"
            },
            "computed": false
          },
          "property": {
            "type": "Identifier",
            "start": 733,
            "end": 739,
            "loc": {
              "start": {
                "line": 18,
                "column": 10
              },
              "end": {
                "line": 18,
                "column": 16
              }
            },
            "name": "propel"
          },
          "computed": false
        },
        "right": {
          "type": "LogicalExpression",
          "start": 742,
          "end": 764,
          "loc": {
            "start": {
              "line": 18,
              "column": 19
            },
            "end": {
              "line": 18,
              "column": 41
            }
          },
          "left": {
            "type": "MemberExpression",
            "start": 742,
            "end": 758,
            "loc": {
              "start": {
                "line": 18,
                "column": 19
              },
              "end": {
                "line": 18,
                "column": 35
              }
            },
            "object": {
              "type": "MemberExpression",
              "start": 742,
              "end": 751,
              "loc": {
                "start": {
                  "line": 18,
                  "column": 19
                },
                "end": {
                  "line": 18,
                  "column": 28
                }
              },
              "object": {
                "type": "Identifier",
                "start": 742,
                "end": 746,
                "loc": {
                  "start": {
                    "line": 18,
                    "column": 19
                  },
                  "end": {
                    "line": 18,
                    "column": 23
                  }
                },
                "name": "self"
              },
              "property": {
                "type": "Identifier",
                "start": 747,
                "end": 751,
                "loc": {
                  "start": {
                    "line": 18,
                    "column": 24
                  },
                  "end": {
                    "line": 18,
                    "column": 28
                  }
                },
                "name": "goog"
              },
              "computed": false
            },
            "property": {
              "type": "Identifier",
              "start": 752,
              "end": 758,
              "loc": {
                "start": {
                  "line": 18,
                  "column": 29
                },
                "end": {
                  "line": 18,
                  "column": 35
                }
              },
              "name": "propel"
            },
            "computed": false
          },
          "operator": "||",
          "right": {
            "type": "ObjectExpression",
            "start": 762,
            "end": 764,
            "loc": {
              "start": {
                "line": 18,
                "column": 39
              },
              "end": {
                "line": 18,
                "column": 41
              }
            },
            "properties": []
          }
        }
      }
    },
    {
      "type": "ExpressionStatement",
      "start": 766,
      "end": 814,
      "loc": {
        "start": {
          "line": 19,
          "column": 0
        },
        "end": {
          "line": 19,
          "column": 48
        }
      },
      "expression": {
        "type": "AssignmentExpression",
        "start": 766,
        "end": 813,
        "loc": {
          "start": {
            "line": 19,
            "column": 0
          },
          "end": {
            "line": 19,
            "column": 47
          }
        },
        "operator": "=",
        "left": {
          "type": "MemberExpression",
          "start": 766,
          "end": 789,
          "loc": {
            "start": {
              "line": 19,
              "column": 0
            },
            "end": {
              "line": 19,
              "column": 23
            }
          },
          "object": {
            "type": "MemberExpression",
            "start": 766,
            "end": 782,
            "loc": {
              "start": {
                "line": 19,
                "column": 0
              },
              "end": {
                "line": 19,
                "column": 16
              }
            },
            "object": {
              "type": "MemberExpression",
              "start": 766,
              "end": 775,
              "loc": {
                "start": {
                  "line": 19,
                  "column": 0
                },
                "end": {
                  "line": 19,
                  "column": 9
                }
              },
              "object": {
                "type": "Identifier",
                "start": 766,
                "end": 770,
                "loc": {
                  "start": {
                    "line": 19,
                    "column": 0
                  },
                  "end": {
                    "line": 19,
                    "column": 4
                  }
                },
                "name": "self"
              },
              "property": {
                "type": "Identifier",
                "start": 771,
                "end": 775,
                "loc": {
                  "start": {
                    "line": 19,
                    "column": 5
                  },
                  "end": {
                    "line": 19,
                    "column": 9
                  }
                },
                "name": "goog"
              },
              "computed": false
            },
            "property": {
              "type": "Identifier",
              "start": 776,
              "end": 782,
              "loc": {
                "start": {
                  "line": 19,
                  "column": 10
                },
                "end": {
                  "line": 19,
                  "column": 16
                }
              },
              "name": "propel"
            },
            "computed": false
          },
          "property": {
            "type": "Identifier",
            "start": 783,
            "end": 789,
            "loc": {
              "start": {
                "line": 19,
                "column": 17
              },
              "end": {
                "line": 19,
                "column": 23
              }
            },
            "name": "worker"
          },
          "computed": false
        },
        "right": {
          "type": "ObjectExpression",
          "start": 792,
          "end": 813,
          "loc": {
            "start": {
              "line": 19,
              "column": 26
            },
            "end": {
              "line": 19,
              "column": 47
            }
          },
          "properties": [
            {
              "type": "Property",
              "start": 793,
              "end": 812,
              "loc": {
                "start": {
                  "line": 19,
                  "column": 27
                },
                "end": {
                  "line": 19,
                  "column": 46
                }
              },
              "method": false,
              "shorthand": true,
              "computed": false,
              "key": {
                "type": "Identifier",
                "start": 793,
                "end": 812,
                "loc": {
                  "start": {
                    "line": 19,
                    "column": 27
                  },
                  "end": {
                    "line": 19,
                    "column": 46
                  }
                },
                "name": "notificationHandler"
              },
              "kind": "init",
              "value": {
                "type": "Identifier",
                "start": 793,
                "end": 812,
                "loc": {
                  "start": {
                    "line": 19,
                    "column": 27
                  },
                  "end": {
                    "line": 19,
                    "column": 46
                  }
                },
                "name": "notificationHandler"
              }
            }
          ]
        }
      }
    }
  ]
}