{
  "type": "Program",
  "body": [
    {
      "type": "ImportDeclaration",
      "specifiers": [
        {
          "type": "ImportDefaultSpecifier",
          "local": {
            "type": "Identifier",
            "name": "notificationHandler",
            "range": [
              635,
              654
            ],
            "loc": {
              "start": {
                "line": 15,
                "column": 7
              },
              "end": {
                "line": 15,
                "column": 26
              }
            }
          },
          "range": [
            635,
            654
          ],
          "loc": {
            "start": {
              "line": 15,
              "column": 7
            },
            "end": {
              "line": 15,
              "column": 26
            }
          }
        }
      ],
      "source": {
        "type": "Literal",
        "value": "./worker/notification-handler",
        "raw": "'./worker/notification-handler'",
        "range": [
          660,
          691
        ],
        "loc": {
          "start": {
            "line": 15,
            "column": 32
          },
          "end": {
            "line": 15,
            "column": 63
          }
        }
      },
      "range": [
        628,
        692
      ],
      "loc": {
        "start": {
          "line": 15,
          "column": 0
        },
        "end": {
          "line": 15,
          "column": 64
        }
      },
      "leadingComments": [
        {
          "type": "Block",
          "value": "\n  Copyright 2015 Google Inc. All Rights Reserved.\n  Licensed under the Apache License, Version 2.0 (the \"License\");\n  you may not use this file except in compliance with the License.\n  You may obtain a copy of the License at\n      http://www.apache.org/licenses/LICENSE-2.0\n  Unless required by applicable law or agreed to in writing, software\n  distributed under the License is distributed on an \"AS IS\" BASIS,\n  WITHOUT WARRANTIES OR CONDITIONS OF ANY KIND, either express or implied.\n  See the License for the specific language governing permissions and\n  limitations under the License.\n",
          "range": [
            0,
            595
          ],
          "loc": {
            "start": {
              "line": 1,
              "column": 0
            },
            "end": {
              "line": 12,
              "column": 2
            }
          }
        },
        {
          "type": "Block",
          "value": " eslint-env serviceworker ",
          "range": [
            596,
            626
          ],
          "loc": {
            "start": {
              "line": 13,
              "column": 0
            },
            "end": {
              "line": 13,
              "column": 30
            }
          }
        }
      ]
    },
    {
      "type": "ExpressionStatement",
      "expression": {
        "type": "AssignmentExpression",
        "operator": "=",
        "left": {
          "type": "MemberExpression",
          "computed": false,
          "object": {
            "type": "Identifier",
            "name": "self",
            "range": [
              694,
              698
            ],
            "loc": {
              "start": {
                "line": 17,
                "column": 0
              },
              "end": {
                "line": 17,
                "column": 4
              }
            }
          },
          "property": {
            "type": "Identifier",
            "name": "goog",
            "range": [
              699,
              703
            ],
            "loc": {
              "start": {
                "line": 17,
                "column": 5
              },
              "end": {
                "line": 17,
                "column": 9
              }
            }
          },
          "range": [
            694,
            703
          ],
          "loc": {
            "start": {
              "line": 17,
              "column": 0
            },
            "end": {
              "line": 17,
              "column": 9
            }
          }
        },
        "right": {
          "type": "LogicalExpression",
          "operator": "||",
          "left": {
            "type": "MemberExpression",
            "computed": false,
            "object": {
              "type": "Identifier",
              "name": "self",
              "range": [
                706,
                710
              ],
              "loc": {
                "start": {
                  "line": 17,
                  "column": 12
                },
                "end": {
                  "line": 17,
                  "column": 16
                }
              }
            },
            "property": {
              "type": "Identifier",
              "name": "goog",
              "range": [
                711,
                715
              ],
              "loc": {
                "start": {
                  "line": 17,
                  "column": 17
                },
                "end": {
                  "line": 17,
                  "column": 21
                }
              }
            },
            "range": [
              706,
              715
            ],
            "loc": {
              "start": {
                "line": 17,
                "column": 12
              },
              "end": {
                "line": 17,
                "column": 21
              }
            }
          },
          "right": {
            "type": "ObjectExpression",
            "properties": [],
            "range": [
              719,
              721
            ],
            "loc": {
              "start": {
                "line": 17,
                "column": 25
              },
              "end": {
                "line": 17,
                "column": 27
              }
            }
          },
          "range": [
            706,
            721
          ],
          "loc": {
            "start": {
              "line": 17,
              "column": 12
            },
            "end": {
              "line": 17,
              "column": 27
            }
          }
        },
        "range": [
          694,
          721
        ],
        "loc": {
          "start": {
            "line": 17,
            "column": 0
          },
          "end": {
            "line": 17,
            "column": 27
          }
        }
      },
      "range": [
        694,
        722
      ],
      "loc": {
        "start": {
          "line": 17,
          "column": 0
        },
        "end": {
          "line": 17,
          "column": 28
        }
      }
    },
    {
      "type": "ExpressionStatement",
      "expression": {
        "type": "AssignmentExpression",
        "operator": "=",
        "left": {
          "type": "MemberExpression",
          "computed": false,
          "object": {
            "type": "MemberExpression",
            "computed": false,
            "object": {
              "type": "Identifier",
              "name": "self",
              "range": [
                723,
                727
              ],
              "loc": {
                "start": {
                  "line": 18,
                  "column": 0
                },
                "end": {
                  "line": 18,
                  "column": 4
                }
              }
            },
            "property": {
              "type": "Identifier",
              "name": "goog",
              "range": [
                728,
                732
              ],
              "loc": {
                "start": {
                  "line": 18,
                  "column": 5
                },
                "end": {
                  "line": 18,
                  "column": 9
                }
              }
            },
            "range": [
              723,
              732
            ],
            "loc": {
              "start": {
                "line": 18,
                "column": 0
              },
              "end": {
                "line": 18,
                "column": 9
              }
            }
          },
          "property": {
            "type": "Identifier",
            "name": "propel",
            "range": [
              733,
              739
            ],
            "loc": {
              "start": {
                "line": 18,
                "column": 10
              },
              "end": {
                "line": 18,
                "column": 16
              }
            }
          },
          "range": [
            723,
            739
          ],
          "loc": {
            "start": {
              "line": 18,
              "column": 0
            },
            "end": {
              "line": 18,
              "column": 16
            }
          }
        },
        "right": {
          "type": "LogicalExpression",
          "operator": "||",
          "left": {
            "type": "MemberExpression",
            "computed": false,
            "object": {
              "type": "MemberExpression",
              "computed": false,
              "object": {
                "type": "Identifier",
                "name": "self",
                "range": [
                  742,
                  746
                ],
                "loc": {
                  "start": {
                    "line": 18,
                    "column": 19
                  },
                  "end": {
                    "line": 18,
                    "column": 23
                  }
                }
              },
              "property": {
                "type": "Identifier",
                "name": "goog",
                "range": [
                  747,
                  751
                ],
                "loc": {
                  "start": {
                    "line": 18,
                    "column": 24
                  },
                  "end": {
                    "line": 18,
                    "column": 28
                  }
                }
              },
              "range": [
                742,
                751
              ],
              "loc": {
                "start": {
                  "line": 18,
                  "column": 19
                },
                "end": {
                  "line": 18,
                  "column": 28
                }
              }
            },
            "property": {
              "type": "Identifier",
              "name": "propel",
              "range": [
                752,
                758
              ],
              "loc": {
                "start": {
                  "line": 18,
                  "column": 29
                },
                "end": {
                  "line": 18,
                  "column": 35
                }
              }
            },
            "range": [
              742,
              758
            ],
            "loc": {
              "start": {
                "line": 18,
                "column": 19
              },
              "end": {
                "line": 18,
                "column": 35
              }
            }
          },
          "right": {
            "type": "ObjectExpression",
            "properties": [],
            "range": [
              762,
              764
            ],
            "loc": {
              "start": {
                "line": 18,
                "column": 39
              },
              "end": {
                "line": 18,
                "column": 41
              }
            }
          },
          "range": [
            742,
            764
          ],
          "loc": {
            "start": {
              "line": 18,
              "column": 19
            },
            "end": {
              "line": 18,
              "column": 41
            }
          }
        },
        "range": [
          723,
          764
        ],
        "loc": {
          "start": {
            "line": 18,
            "column": 0
          },
          "end": {
            "line": 18,
            "column": 41
          }
        }
      },
      "range": [
        723,
        765
      ],
      "loc": {
        "start": {
          "line": 18,
          "column": 0
        },
        "end": {
          "line": 18,
          "column": 42
        }
      }
    },
    {
      "type": "ExpressionStatement",
      "expression": {
        "type": "AssignmentExpression",
        "operator": "=",
        "left": {
          "type": "MemberExpression",
          "computed": false,
          "object": {
            "type": "MemberExpression",
            "computed": false,
            "object": {
              "type": "MemberExpression",
              "computed": false,
              "object": {
                "type": "Identifier",
                "name": "self",
                "range": [
                  766,
                  770
                ],
                "loc": {
                  "start": {
                    "line": 19,
                    "column": 0
                  },
                  "end": {
                    "line": 19,
                    "column": 4
                  }
                }
              },
              "property": {
                "type": "Identifier",
                "name": "goog",
                "range": [
                  771,
                  775
                ],
                "loc": {
                  "start": {
                    "line": 19,
                    "column": 5
                  },
                  "end": {
                    "line": 19,
                    "column": 9
                  }
                }
              },
              "range": [
                766,
                775
              ],
              "loc": {
                "start": {
                  "line": 19,
                  "column": 0
                },
                "end": {
                  "line": 19,
                  "column": 9
                }
              }
            },
            "property": {
              "type": "Identifier",
              "name": "propel",
              "range": [
                776,
                782
              ],
              "loc": {
                "start": {
                  "line": 19,
                  "column": 10
                },
                "end": {
                  "line": 19,
                  "column": 16
                }
              }
            },
            "range": [
              766,
              782
            ],
            "loc": {
              "start": {
                "line": 19,
                "column": 0
              },
              "end": {
                "line": 19,
                "column": 16
              }
            }
          },
          "property": {
            "type": "Identifier",
            "name": "worker",
            "range": [
              783,
              789
            ],
            "loc": {
              "start": {
                "line": 19,
                "column": 17
              },
              "end": {
                "line": 19,
                "column": 23
              }
            }
          },
          "range": [
            766,
            789
          ],
          "loc": {
            "start": {
              "line": 19,
              "column": 0
            },
            "end": {
              "line": 19,
              "column": 23
            }
          }
        },
        "right": {
          "type": "ObjectExpression",
          "properties": [
            {
              "type": "Property",
              "key": {
                "type": "Identifier",
                "name": "notificationHandler",
                "range": [
                  793,
                  812
                ],
                "loc": {
                  "start": {
                    "line": 19,
                    "column": 27
                  },
                  "end": {
                    "line": 19,
                    "column": 46
                  }
                }
              },
              "value": {
                "type": "Identifier",
                "name": "notificationHandler",
                "range": [
                  793,
                  812
                ],
                "loc": {
                  "start": {
                    "line": 19,
                    "column": 27
                  },
                  "end": {
                    "line": 19,
                    "column": 46
                  }
                }
              },
              "kind": "init",
              "method": false,
              "shorthand": true,
              "computed": false,
              "range": [
                793,
                812
              ],
              "loc": {
                "start": {
                  "line": 19,
                  "column": 27
                },
                "end": {
                  "line": 19,
                  "column": 46
                }
              }
            }
          ],
          "range": [
            792,
            813
          ],
          "loc": {
            "start": {
              "line": 19,
              "column": 26
            },
            "end": {
              "line": 19,
              "column": 47
            }
          }
        },
        "range": [
          766,
          813
        ],
        "loc": {
          "start": {
            "line": 19,
            "column": 0
          },
          "end": {
            "line": 19,
            "column": 47
          }
        }
      },
      "range": [
        766,
        814
      ],
      "loc": {
        "start": {
          "line": 19,
          "column": 0
        },
        "end": {
          "line": 19,
          "column": 48
        }
      }
    }
  ],
  "sourceType": "module",
  "range": [
    628,
    814
  ],
  "loc": {
    "start": {
      "line": 15,
      "column": 0
    },
    "end": {
      "line": 19,
      "column": 48
    }
  },
  "comments": [
    {
      "type": "Block",
      "value": "\n  Copyright 2015 Google Inc. All Rights Reserved.\n  Licensed under the Apache License, Version 2.0 (the \"License\");\n  you may not use this file except in compliance with the License.\n  You may obtain a copy of the License at\n      http://www.apache.org/licenses/LICENSE-2.0\n  Unless required by applicable law or agreed to in writing, software\n  distributed under the License is distributed on an \"AS IS\" BASIS,\n  WITHOUT WARRANTIES OR CONDITIONS OF ANY KIND, either express or implied.\n  See the License for the specific language governing permissions and\n  limitations under the License.\n",
      "range": [
        0,
        595
      ],
      "loc": {
        "start": {
          "line": 1,
          "column": 0
        },
        "end": {
          "line": 12,
          "column": 2
        }
      }
    },
    {
      "type": "Block",
      "value": " eslint-env serviceworker ",
      "range": [
        596,
        626
      ],
      "loc": {
        "start": {
          "line": 13,
          "column": 0
        },
        "end": {
          "line": 13,
          "column": 30
        }
      }
    }
  ]
}